{
    "@context": "http://iiif.io/api/presentation/2/context.json",
    "@id": "https://readux.io/iiif/v2/t1114/list/t1114_00000119.jpg",
    "@type": "sc:AnnotationList",
    "resources": [
        {
            "@context": "http://iiif.io/api/presentation/2/context.json",
            "@id": "35e0d2d8-94a2-4759-81e7-a1740638cb0d",
            "@type": "oa:Annotation",
            "motivation": "sc:painting",
            "annotatedBy": {
                "name": "OCR"
            },
            "resource": {
                "@type": "cnt:ContentAsText",
                "format": "text/html",
                "chars": "<span id='35e0d2d8-94a2-4759-81e7-a1740638cb0d' class='anno-35e0d2d8-94a2-4759-81e7-a1740638cb0d' data-letter-spacing='-2.4375'>I</span>",
                "language": "en"
            },
            "on": {
                "full": "https://readux.io/iiif/v2/t1114/canvas/t1114_00000119.jpg",
                "@type": "oa:SpecificResource",
                "within": {
                    "@id": "https://readux.io/iiif/v2/t1114/manifest",
                    "@type": "sc:Manifest"
                },
                "selector": {
                    "@type": "oa:FragmentSelector",
                    "value": "xywh=3500,3873,4,44",
                    "item": {
                        "@type": "oa:FragmentSelector"
                    }
                }
            },
            "stylesheet": {
                "type": "CssStylesheet",
                "value": ".anno-35e0d2d8-94a2-4759-81e7-a1740638cb0d: { height: 44px; width: 4px; font-size: 27.5px; letter-spacing: -9.75px;}"
            }
        },
        {
            "@context": "http://iiif.io/api/presentation/2/context.json",
            "@id": "279adc4e-c98f-40ad-bb70-2e029c705f7b",
            "@type": "oa:Annotation",
            "motivation": "sc:painting",
            "annotatedBy": {
                "name": "OCR"
            },
            "resource": {
                "@type": "cnt:ContentAsText",
                "format": "text/html",
                "chars": "<span id='279adc4e-c98f-40ad-bb70-2e029c705f7b' class='anno-279adc4e-c98f-40ad-bb70-2e029c705f7b' data-letter-spacing='0.08586816490123103'>FONTANA</span>",
                "language": "en"
            },
            "on": {
                "full": "https://readux.io/iiif/v2/t1114/canvas/t1114_00000119.jpg",
                "@type": "oa:SpecificResource",
                "within": {
                    "@id": "https://readux.io/iiif/v2/t1114/manifest",
                    "@type": "sc:Manifest"
                },
                "selector": {
                    "@type": "oa:FragmentSelector",
                    "value": "xywh=1054,4202,499,91",
                    "item": {
                        "@type": "oa:FragmentSelector"
                    }
                }
            },
            "stylesheet": {
                "type": "CssStylesheet",
                "value": ".anno-279adc4e-c98f-40ad-bb70-2e029c705f7b: { height: 91px; width: 499px; font-size: 56.875px; letter-spacing: 42.848214285714285px;}"
            }
        },
        {
            "@context": "http://iiif.io/api/presentation/2/context.json",
            "@id": "46de8dc6-e05e-416d-b6e0-f94a4a59ee31",
            "@type": "oa:Annotation",
            "motivation": "sc:painting",
            "annotatedBy": {
                "name": "OCR"
            },
            "resource": {
                "@type": "cnt:ContentAsText",
                "format": "text/html",
                "chars": "<span id='46de8dc6-e05e-416d-b6e0-f94a4a59ee31' class='anno-46de8dc6-e05e-416d-b6e0-f94a4a59ee31' data-letter-spacing='0.1231283422459893'>DETTA</span>",
                "language": "en"
            },
            "on": {
                "full": "https://readux.io/iiif/v2/t1114/canvas/t1114_00000119.jpg",
                "@type": "oa:SpecificResource",
                "within": {
                    "@id": "https://readux.io/iiif/v2/t1114/manifest",
                    "@type": "sc:Manifest"
                },
                "selector": {
                    "@type": "oa:FragmentSelector",
                    "value": "xywh=1611,4198,374,92",
                    "item": {
                        "@type": "oa:FragmentSelector"
                    }
                }
            },
            "stylesheet": {
                "type": "CssStylesheet",
                "value": ".anno-46de8dc6-e05e-416d-b6e0-f94a4a59ee31: { height: 92px; width: 374px; font-size: 57.5px; letter-spacing: 46.05px;}"
            }
        },
        {
            "@context": "http://iiif.io/api/presentation/2/context.json",
            "@id": "c8d4a3fc-0d59-4630-8c32-3016e5d8ebd6",
            "@type": "oa:Annotation",
            "motivation": "sc:painting",
            "annotatedBy": {
                "name": "OCR"
            },
            "resource": {
                "@type": "cnt:ContentAsText",
                "format": "text/html",
                "chars": "<span id='c8d4a3fc-0d59-4630-8c32-3016e5d8ebd6' class='anno-c8d4a3fc-0d59-4630-8c32-3016e5d8ebd6' data-letter-spacing='0.10814696485623004'>DELLA</span>",
                "language": "en"
            },
            "on": {
                "full": "https://readux.io/iiif/v2/t1114/canvas/t1114_00000119.jpg",
                "@type": "oa:SpecificResource",
                "within": {
                    "@id": "https://readux.io/iiif/v2/t1114/manifest",
                    "@type": "sc:Manifest"
                },
                "selector": {
                    "@type": "oa:FragmentSelector",
                    "value": "xywh=2067,4196,313,92",
                    "item": {
                        "@type": "oa:FragmentSelector"
                    }
                }
            },
            "stylesheet": {
                "type": "CssStylesheet",
                "value": ".anno-c8d4a3fc-0d59-4630-8c32-3016e5d8ebd6: { height: 92px; width: 313px; font-size: 57.5px; letter-spacing: 33.85px;}"
            }
        },
        {
            "@context": "http://iiif.io/api/presentation/2/context.json",
            "@id": "f288913c-4895-4b6f-8cd6-fd4946500c63",
            "@type": "oa:Annotation",
            "motivation": "sc:painting",
            "annotatedBy": {
                "name": "OCR"
            },
            "resource": {
                "@type": "cnt:ContentAsText",
                "format": "text/html",
                "chars": "<span id='f288913c-4895-4b6f-8cd6-fd4946500c63' class='anno-f288913c-4895-4b6f-8cd6-fd4946500c63' data-letter-spacing='0.07299536401098901'>PIOGGIA</span>",
                "language": "en"
            },
            "on": {
                "full": "https://readux.io/iiif/v2/t1114/canvas/t1114_00000119.jpg",
                "@type": "oa:SpecificResource",
                "within": {
                    "@id": "https://readux.io/iiif/v2/t1114/manifest",
                    "@type": "sc:Manifest"
                },
                "selector": {
                    "@type": "oa:FragmentSelector",
                    "value": "xywh=2459,4193,416,93",
                    "item": {
                        "@type": "oa:FragmentSelector"
                    }
                }
            },
            "stylesheet": {
                "type": "CssStylesheet",
                "value": ".anno-f288913c-4895-4b6f-8cd6-fd4946500c63: { height: 93px; width: 416px; font-size: 58.125px; letter-spacing: 30.366071428571427px;}"
            }
        },
        {
            "@context": "http://iiif.io/api/presentation/2/context.json",
            "@id": "59327308-d406-4480-bf31-46662150fa5e",
            "@type": "oa:Annotation",
            "motivation": "sc:painting",
            "annotatedBy": {
                "name": "OCR"
            },
            "resource": {
                "@type": "cnt:ContentAsText",
                "format": "text/html",
                "chars": "<span id='59327308-d406-4480-bf31-46662150fa5e' class='anno-59327308-d406-4480-bf31-46662150fa5e' data-letter-spacing='0.19815891472868216'>NEL</span>",
                "language": "en"
            },
            "on": {
                "full": "https://readux.io/iiif/v2/t1114/canvas/t1114_00000119.jpg",
                "@type": "oa:SpecificResource",
                "within": {
                    "@id": "https://readux.io/iiif/v2/t1114/manifest",
                    "@type": "sc:Manifest"
                },
                "selector": {
                    "@type": "oa:FragmentSelector",
                    "value": "xywh=2944,4190,215,93",
                    "item": {
                        "@type": "oa:FragmentSelector"
                    }
                }
            },
            "stylesheet": {
                "type": "CssStylesheet",
                "value": ".anno-59327308-d406-4480-bf31-46662150fa5e: { height: 93px; width: 215px; font-size: 58.125px; letter-spacing: 42.604166666666664px;}"
            }
        },
        {
            "@context": "http://iiif.io/api/presentation/2/context.json",
            "@id": "ba976dca-2fb3-41d3-965e-58229c128a70",
            "@type": "oa:Annotation",
            "motivation": "sc:painting",
            "annotatedBy": {
                "name": "OCR"
            },
            "resource": {
                "@type": "cnt:ContentAsText",
                "format": "text/html",
                "chars": "<span id='ba976dca-2fb3-41d3-965e-58229c128a70' class='anno-ba976dca-2fb3-41d3-965e-58229c128a70' data-letter-spacing='0.07093631178707224'>GIARDINO</span>",
                "language": "en"
            },
            "on": {
                "full": "https://readux.io/iiif/v2/t1114/canvas/t1114_00000119.jpg",
                "@type": "oa:SpecificResource",
                "within": {
                    "@id": "https://readux.io/iiif/v2/t1114/manifest",
                    "@type": "sc:Manifest"
                },
                "selector": {
                    "@type": "oa:FragmentSelector",
                    "value": "xywh=3239,4189,526,91",
                    "item": {
                        "@type": "oa:FragmentSelector"
                    }
                }
            },
            "stylesheet": {
                "type": "CssStylesheet",
                "value": ".anno-ba976dca-2fb3-41d3-965e-58229c128a70: { height: 91px; width: 526px; font-size: 56.875px; letter-spacing: 37.3125px;}"
            }
        },
        {
            "@context": "http://iiif.io/api/presentation/2/context.json",
            "@id": "f74a0acd-8aac-4333-9baf-a5f777b1665e",
            "@type": "oa:Annotation",
            "motivation": "sc:painting",
            "annotatedBy": {
                "name": "OCR"
            },
            "resource": {
                "@type": "cnt:ContentAsText",
                "format": "text/html",
                "chars": "<span id='f74a0acd-8aac-4333-9baf-a5f777b1665e' class='anno-f74a0acd-8aac-4333-9baf-a5f777b1665e' data-letter-spacing='0.16979706390328153'>DEL</span>",
                "language": "en"
            },
            "on": {
                "full": "https://readux.io/iiif/v2/t1114/canvas/t1114_00000119.jpg",
                "@type": "oa:SpecificResource",
                "within": {
                    "@id": "https://readux.io/iiif/v2/t1114/manifest",
                    "@type": "sc:Manifest"
                },
                "selector": {
                    "@type": "oa:FragmentSelector",
                    "value": "xywh=3861,4177,193,101",
                    "item": {
                        "@type": "oa:FragmentSelector"
                    }
                }
            },
            "stylesheet": {
                "type": "CssStylesheet",
                "value": ".anno-f74a0acd-8aac-4333-9baf-a5f777b1665e: { height: 101px; width: 193px; font-size: 63.125px; letter-spacing: 32.770833333333336px;}"
            }
        },
        {
            "@context": "http://iiif.io/api/presentation/2/context.json",
            "@id": "04c93070-efe0-4719-9118-d20d48d03e6d",
            "@type": "oa:Annotation",
            "motivation": "sc:painting",
            "annotatedBy": {
                "name": "OCR"
            },
            "resource": {
                "@type": "cnt:ContentAsText",
                "format": "text/html",
                "chars": "<span id='04c93070-efe0-4719-9118-d20d48d03e6d' class='anno-04c93070-efe0-4719-9118-d20d48d03e6d' data-letter-spacing='0.07935110663983903'>PALAZZO</span>",
                "language": "en"
            },
            "on": {
                "full": "https://readux.io/iiif/v2/t1114/canvas/t1114_00000119.jpg",
                "@type": "oa:SpecificResource",
                "within": {
                    "@id": "https://readux.io/iiif/v2/t1114/manifest",
                    "@type": "sc:Manifest"
                },
                "selector": {
                    "@type": "oa:FragmentSelector",
                    "value": "xywh=4123,4176,497,101",
                    "item": {
                        "@type": "oa:FragmentSelector"
                    }
                }
            },
            "stylesheet": {
                "type": "CssStylesheet",
                "value": ".anno-04c93070-efe0-4719-9118-d20d48d03e6d: { height: 101px; width: 497px; font-size: 63.125px; letter-spacing: 39.4375px;}"
            }
        },
        {
            "@context": "http://iiif.io/api/presentation/2/context.json",
            "@id": "07530a2d-78b1-4c66-ae4a-cb42a7c2e6ce",
            "@type": "oa:Annotation",
            "motivation": "sc:painting",
            "annotatedBy": {
                "name": "OCR"
            },
            "resource": {
                "@type": "cnt:ContentAsText",
                "format": "text/html",
                "chars": "<span id='07530a2d-78b1-4c66-ae4a-cb42a7c2e6ce' class='anno-07530a2d-78b1-4c66-ae4a-cb42a7c2e6ce' data-letter-spacing='0.04791666666666667'>PONTIFICIO</span>",
                "language": "en"
            },
            "on": {
                "full": "https://readux.io/iiif/v2/t1114/canvas/t1114_00000119.jpg",
                "@type": "oa:SpecificResource",
                "within": {
                    "@id": "https://readux.io/iiif/v2/t1114/manifest",
                    "@type": "sc:Manifest"
                },
                "selector": {
                    "@type": "oa:FragmentSelector",
                    "value": "xywh=4712,4173,606,101",
                    "item": {
                        "@type": "oa:FragmentSelector"
                    }
                }
            },
            "stylesheet": {
                "type": "CssStylesheet",
                "value": ".anno-07530a2d-78b1-4c66-ae4a-cb42a7c2e6ce: { height: 101px; width: 606px; font-size: 63.125px; letter-spacing: 29.0375px;}"
            }
        },
        {
            "@context": "http://iiif.io/api/presentation/2/context.json",
            "@id": "885d107a-1810-4fe7-8f9f-7bcc5bb6f149",
            "@type": "oa:Annotation",
            "motivation": "sc:painting",
            "annotatedBy": {
                "name": "OCR"
            },
            "resource": {
                "@type": "cnt:ContentAsText",
                "format": "text/html",
                "chars": "<span id='885d107a-1810-4fe7-8f9f-7bcc5bb6f149' class='anno-885d107a-1810-4fe7-8f9f-7bcc5bb6f149' data-letter-spacing='0.1891025641025641'>SVL</span>",
                "language": "en"
            },
            "on": {
                "full": "https://readux.io/iiif/v2/t1114/canvas/t1114_00000119.jpg",
                "@type": "oa:SpecificResource",
                "within": {
                    "@id": "https://readux.io/iiif/v2/t1114/manifest",
                    "@type": "sc:Manifest"
                },
                "selector": {
                    "@type": "oa:FragmentSelector",
                    "value": "xywh=5404,4170,221,102",
                    "item": {
                        "@type": "oa:FragmentSelector"
                    }
                }
            },
            "stylesheet": {
                "type": "CssStylesheet",
                "value": ".anno-885d107a-1810-4fe7-8f9f-7bcc5bb6f149: { height: 102px; width: 221px; font-size: 63.75px; letter-spacing: 41.791666666666664px;}"
            }
        },
        {
            "@context": "http://iiif.io/api/presentation/2/context.json",
            "@id": "24915ef6-d9d5-448a-bcbb-b6f851b68953",
            "@type": "oa:Annotation",
            "motivation": "sc:painting",
            "annotatedBy": {
                "name": "OCR"
            },
            "resource": {
                "@type": "cnt:ContentAsText",
                "format": "text/html",
                "chars": "<span id='24915ef6-d9d5-448a-bcbb-b6f851b68953' class='anno-24915ef6-d9d5-448a-bcbb-b6f851b68953' data-letter-spacing='0.04419462288841304'>QVIRINALE</span>",
                "language": "en"
            },
            "on": {
                "full": "https://readux.io/iiif/v2/t1114/canvas/t1114_00000119.jpg",
                "@type": "oa:SpecificResource",
                "within": {
                    "@id": "https://readux.io/iiif/v2/t1114/manifest",
                    "@type": "sc:Manifest"
                },
                "selector": {
                    "@type": "oa:FragmentSelector",
                    "value": "xywh=5676,4170,467,100",
                    "item": {
                        "@type": "oa:FragmentSelector"
                    }
                }
            },
            "stylesheet": {
                "type": "CssStylesheet",
                "value": ".anno-24915ef6-d9d5-448a-bcbb-b6f851b68953: { height: 100px; width: 467px; font-size: 62.5px; letter-spacing: 20.63888888888889px;}"
            }
        },
        {
            "@context": "http://iiif.io/api/presentation/2/context.json",
            "@id": "889d8246-f803-47a6-9ebc-0d3db86e36d2",
            "@type": "oa:Annotation",
            "motivation": "sc:painting",
            "annotatedBy": {
                "name": "OCR"
            },
            "resource": {
                "@type": "cnt:ContentAsText",
                "format": "text/html",
                "chars": "<span id='889d8246-f803-47a6-9ebc-0d3db86e36d2' class='anno-889d8246-f803-47a6-9ebc-0d3db86e36d2' data-letter-spacing='-0.15056818181818182'>a</span>",
                "language": "en"
            },
            "on": {
                "full": "https://readux.io/iiif/v2/t1114/canvas/t1114_00000119.jpg",
                "@type": "oa:SpecificResource",
                "within": {
                    "@id": "https://readux.io/iiif/v2/t1114/manifest",
                    "@type": "sc:Manifest"
                },
                "selector": {
                    "@type": "oa:FragmentSelector",
                    "value": "xywh=3023,4277,22,81",
                    "item": {
                        "@type": "oa:FragmentSelector"
                    }
                }
            },
            "stylesheet": {
                "type": "CssStylesheet",
                "value": ".anno-889d8246-f803-47a6-9ebc-0d3db86e36d2: { height: 81px; width: 22px; font-size: 50.625px; letter-spacing: -3.3125px;}"
            }
        },
        {
            "@context": "http://iiif.io/api/presentation/2/context.json",
            "@id": "239b2821-c84c-4866-a715-9795d9b96c4f",
            "@type": "oa:Annotation",
            "motivation": "sc:painting",
            "annotatedBy": {
                "name": "OCR"
            },
            "resource": {
                "@type": "cnt:ContentAsText",
                "format": "text/html",
                "chars": "<span id='239b2821-c84c-4866-a715-9795d9b96c4f' class='anno-239b2821-c84c-4866-a715-9795d9b96c4f' data-letter-spacing='0.08597972972972973'>monte</span>",
                "language": "en"
            },
            "on": {
                "full": "https://readux.io/iiif/v2/t1114/canvas/t1114_00000119.jpg",
                "@type": "oa:SpecificResource",
                "within": {
                    "@id": "https://readux.io/iiif/v2/t1114/manifest",
                    "@type": "sc:Manifest"
                },
                "selector": {
                    "@type": "oa:FragmentSelector",
                    "value": "xywh=3085,4277,222,81",
                    "item": {
                        "@type": "oa:FragmentSelector"
                    }
                }
            },
            "stylesheet": {
                "type": "CssStylesheet",
                "value": ".anno-239b2821-c84c-4866-a715-9795d9b96c4f: { height: 81px; width: 222px; font-size: 50.625px; letter-spacing: 19.0875px;}"
            }
        },
        {
            "@context": "http://iiif.io/api/presentation/2/context.json",
            "@id": "00d53898-92b9-49c8-9c20-734a6487008a",
            "@type": "oa:Annotation",
            "motivation": "sc:painting",
            "annotatedBy": {
                "name": "OCR"
            },
            "resource": {
                "@type": "cnt:ContentAsText",
                "format": "text/html",
                "chars": "<span id='00d53898-92b9-49c8-9c20-734a6487008a' class='anno-00d53898-92b9-49c8-9c20-734a6487008a' data-letter-spacing='0.047697368421052634'>Cauallo</span>",
                "language": "en"
            },
            "on": {
                "full": "https://readux.io/iiif/v2/t1114/canvas/t1114_00000119.jpg",
                "@type": "oa:SpecificResource",
                "within": {
                    "@id": "https://readux.io/iiif/v2/t1114/manifest",
                    "@type": "sc:Manifest"
                },
                "selector": {
                    "@type": "oa:FragmentSelector",
                    "value": "xywh=3331,4277,266,81",
                    "item": {
                        "@type": "oa:FragmentSelector"
                    }
                }
            },
            "stylesheet": {
                "type": "CssStylesheet",
                "value": ".anno-00d53898-92b9-49c8-9c20-734a6487008a: { height: 81px; width: 266px; font-size: 50.625px; letter-spacing: 12.6875px;}"
            }
        },
        {
            "@context": "http://iiif.io/api/presentation/2/context.json",
            "@id": "85dc45fd-c7bb-4352-a86d-03992e576799",
            "@type": "oa:Annotation",
            "motivation": "sc:painting",
            "annotatedBy": {
                "name": "OCR"
            },
            "resource": {
                "@type": "cnt:ContentAsText",
                "format": "text/html",
                "chars": "<span id='85dc45fd-c7bb-4352-a86d-03992e576799' class='anno-85dc45fd-c7bb-4352-a86d-03992e576799' data-letter-spacing='0.09226190476190477'>nel</span>",
                "language": "en"
            },
            "on": {
                "full": "https://readux.io/iiif/v2/t1114/canvas/t1114_00000119.jpg",
                "@type": "oa:SpecificResource",
                "within": {
                    "@id": "https://readux.io/iiif/v2/t1114/manifest",
                    "@type": "sc:Manifest"
                },
                "selector": {
                    "@type": "oa:FragmentSelector",
                    "value": "xywh=3634,4277,105,81",
                    "item": {
                        "@type": "oa:FragmentSelector"
                    }
                }
            },
            "stylesheet": {
                "type": "CssStylesheet",
                "value": ".anno-85dc45fd-c7bb-4352-a86d-03992e576799: { height: 81px; width: 105px; font-size: 50.625px; letter-spacing: 9.6875px;}"
            }
        },
        {
            "@context": "http://iiif.io/api/presentation/2/context.json",
            "@id": "a315865f-6a94-429c-b291-b4b32593cb10",
            "@type": "oa:Annotation",
            "motivation": "sc:painting",
            "annotatedBy": {
                "name": "OCR"
            },
            "resource": {
                "@type": "cnt:ContentAsText",
                "format": "text/html",
                "chars": "<span id='a315865f-6a94-429c-b291-b4b32593cb10' class='anno-a315865f-6a94-429c-b291-b4b32593cb10' data-letter-spacing='0.07085459183673469'>primo</span>",
                "language": "en"
            },
            "on": {
                "full": "https://readux.io/iiif/v2/t1114/canvas/t1114_00000119.jpg",
                "@type": "oa:SpecificResource",
                "within": {
                    "@id": "https://readux.io/iiif/v2/t1114/manifest",
                    "@type": "sc:Manifest"
                },
                "selector": {
                    "@type": "oa:FragmentSelector",
                    "value": "xywh=3783,4277,196,81",
                    "item": {
                        "@type": "oa:FragmentSelector"
                    }
                }
            },
            "stylesheet": {
                "type": "CssStylesheet",
                "value": ".anno-a315865f-6a94-429c-b291-b4b32593cb10: { height: 81px; width: 196px; font-size: 50.625px; letter-spacing: 13.8875px;}"
            }
        },
        {
            "@context": "http://iiif.io/api/presentation/2/context.json",
            "@id": "57d60980-d73c-472d-a7a5-7e685a9a39c2",
            "@type": "oa:Annotation",
            "motivation": "sc:painting",
            "annotatedBy": {
                "name": "OCR"
            },
            "resource": {
                "@type": "cnt:ContentAsText",
                "format": "text/html",
                "chars": "<span id='57d60980-d73c-472d-a7a5-7e685a9a39c2' class='anno-57d60980-d73c-472d-a7a5-7e685a9a39c2' data-letter-spacing='0.06243206521739131'>piano</span>",
                "language": "en"
            },
            "on": {
                "full": "https://readux.io/iiif/v2/t1114/canvas/t1114_00000119.jpg",
                "@type": "oa:SpecificResource",
                "within": {
                    "@id": "https://readux.io/iiif/v2/t1114/manifest",
                    "@type": "sc:Manifest"
                },
                "selector": {
                    "@type": "oa:FragmentSelector",
                    "value": "xywh=4022,4277,184,81",
                    "item": {
                        "@type": "oa:FragmentSelector"
                    }
                }
            },
            "stylesheet": {
                "type": "CssStylesheet",
                "value": ".anno-57d60980-d73c-472d-a7a5-7e685a9a39c2: { height: 81px; width: 184px; font-size: 50.625px; letter-spacing: 11.4875px;}"
            }
        },
        {
            "@context": "http://iiif.io/api/presentation/2/context.json",
            "@id": "6bf48ee3-20eb-4842-b25a-95b10f2c159e",
            "@type": "oa:Annotation",
            "motivation": "sc:painting",
            "annotatedBy": {
                "name": "OCR"
            },
            "resource": {
                "@type": "cnt:ContentAsText",
                "format": "text/html",
                "chars": "<span id='6bf48ee3-20eb-4842-b25a-95b10f2c159e' class='anno-6bf48ee3-20eb-4842-b25a-95b10f2c159e' data-letter-spacing='-0.10054347826086957'>.</span>",
                "language": "en"
            },
            "on": {
                "full": "https://readux.io/iiif/v2/t1114/canvas/t1114_00000119.jpg",
                "@type": "oa:SpecificResource",
                "within": {
                    "@id": "https://readux.io/iiif/v2/t1114/manifest",
                    "@type": "sc:Manifest"
                },
                "selector": {
                    "@type": "oa:FragmentSelector",
                    "value": "xywh=4207,4277,23,81",
                    "item": {
                        "@type": "oa:FragmentSelector"
                    }
                }
            },
            "stylesheet": {
                "type": "CssStylesheet",
                "value": ".anno-6bf48ee3-20eb-4842-b25a-95b10f2c159e: { height: 81px; width: 23px; font-size: 50.625px; letter-spacing: -2.3125px;}"
            }
        },
        {
            "@context": "http://iiif.io/api/presentation/2/context.json",
            "@id": "fa0f0c41-0c6a-4477-a8c9-513174cc2953",
            "@type": "oa:Annotation",
            "motivation": "sc:painting",
            "annotatedBy": {
                "name": "OCR"
            },
            "resource": {
                "@type": "cnt:ContentAsText",
                "format": "text/html",
                "chars": "<span id='fa0f0c41-0c6a-4477-a8c9-513174cc2953' class='anno-fa0f0c41-0c6a-4477-a8c9-513174cc2953' data-letter-spacing='0.11071428571428571'>ALTRA</span>",
                "language": "en"
            },
            "on": {
                "full": "https://readux.io/iiif/v2/t1114/canvas/t1114_00000119.jpg",
                "@type": "oa:SpecificResource",
                "within": {
                    "@id": "https://readux.io/iiif/v2/t1114/manifest",
                    "@type": "sc:Manifest"
                },
                "selector": {
                    "@type": "oa:FragmentSelector",
                    "value": "xywh=1270,4386,280,80",
                    "item": {
                        "@type": "oa:FragmentSelector"
                    }
                }
            },
            "stylesheet": {
                "type": "CssStylesheet",
                "value": ".anno-fa0f0c41-0c6a-4477-a8c9-513174cc2953: { height: 80px; width: 280px; font-size: 50.0px; letter-spacing: 31.0px;}"
            }
        },
        {
            "@context": "http://iiif.io/api/presentation/2/context.json",
            "@id": "a54a5645-b40b-4b60-95d9-c2fbfc7f2f0e",
            "@type": "oa:Annotation",
            "motivation": "sc:painting",
            "annotatedBy": {
                "name": "OCR"
            },
            "resource": {
                "@type": "cnt:ContentAsText",
                "format": "text/html",
                "chars": "<span id='a54a5645-b40b-4b60-95d9-c2fbfc7f2f0e' class='anno-a54a5645-b40b-4b60-95d9-c2fbfc7f2f0e' data-letter-spacing='0.0993461879432624'>VEDVTA</span>",
                "language": "en"
            },
            "on": {
                "full": "https://readux.io/iiif/v2/t1114/canvas/t1114_00000119.jpg",
                "@type": "oa:SpecificResource",
                "within": {
                    "@id": "https://readux.io/iiif/v2/t1114/manifest",
                    "@type": "sc:Manifest"
                },
                "selector": {
                    "@type": "oa:FragmentSelector",
                    "value": "xywh=1631,4381,376,81",
                    "item": {
                        "@type": "oa:FragmentSelector"
                    }
                }
            },
            "stylesheet": {
                "type": "CssStylesheet",
                "value": ".anno-a54a5645-b40b-4b60-95d9-c2fbfc7f2f0e: { height: 81px; width: 376px; font-size: 50.625px; letter-spacing: 37.354166666666664px;}"
            }
        },
        {
            "@context": "http://iiif.io/api/presentation/2/context.json",
            "@id": "6fd8e979-37a0-4fd4-996c-42cc1e507b6d",
            "@type": "oa:Annotation",
            "motivation": "sc:painting",
            "annotatedBy": {
                "name": "OCR"
            },
            "resource": {
                "@type": "cnt:ContentAsText",
                "format": "text/html",
                "chars": "<span id='6fd8e979-37a0-4fd4-996c-42cc1e507b6d' class='anno-6fd8e979-37a0-4fd4-996c-42cc1e507b6d' data-letter-spacing='-0.05'>E</span>",
                "language": "en"
            },
            "on": {
                "full": "https://readux.io/iiif/v2/t1114/canvas/t1114_00000119.jpg",
                "@type": "oa:SpecificResource",
                "within": {
                    "@id": "https://readux.io/iiif/v2/t1114/manifest",
                    "@type": "sc:Manifest"
                },
                "selector": {
                    "@type": "oa:FragmentSelector",
                    "value": "xywh=2100,4377,25,84",
                    "item": {
                        "@type": "oa:FragmentSelector"
                    }
                }
            },
            "stylesheet": {
                "type": "CssStylesheet",
                "value": ".anno-6fd8e979-37a0-4fd4-996c-42cc1e507b6d: { height: 84px; width: 25px; font-size: 52.5px; letter-spacing: -1.25px;}"
            }
        },
        {
            "@context": "http://iiif.io/api/presentation/2/context.json",
            "@id": "d7f37c2c-ddb9-47bd-9b6b-e5ef2bab9e1f",
            "@type": "oa:Annotation",
            "motivation": "sc:painting",
            "annotatedBy": {
                "name": "OCR"
            },
            "resource": {
                "@type": "cnt:ContentAsText",
                "format": "text/html",
                "chars": "<span id='d7f37c2c-ddb9-47bd-9b6b-e5ef2bab9e1f' class='anno-d7f37c2c-ddb9-47bd-9b6b-e5ef2bab9e1f' data-letter-spacing='0.07956600361663653'>PIOGGIA</span>",
                "language": "en"
            },
            "on": {
                "full": "https://readux.io/iiif/v2/t1114/canvas/t1114_00000119.jpg",
                "@type": "oa:SpecificResource",
                "within": {
                    "@id": "https://readux.io/iiif/v2/t1114/manifest",
                    "@type": "sc:Manifest"
                },
                "selector": {
                    "@type": "oa:FragmentSelector",
                    "value": "xywh=2213,4376,395,80",
                    "item": {
                        "@type": "oa:FragmentSelector"
                    }
                }
            },
            "stylesheet": {
                "type": "CssStylesheet",
                "value": ".anno-d7f37c2c-ddb9-47bd-9b6b-e5ef2bab9e1f: { height: 80px; width: 395px; font-size: 50.0px; letter-spacing: 31.428571428571427px;}"
            }
        },
        {
            "@context": "http://iiif.io/api/presentation/2/context.json",
            "@id": "94c17492-3c9c-4b16-a891-90d97603c5c9",
            "@type": "oa:Annotation",
            "motivation": "sc:painting",
            "annotatedBy": {
                "name": "OCR"
            },
            "resource": {
                "@type": "cnt:ContentAsText",
                "format": "text/html",
                "chars": "<span id='94c17492-3c9c-4b16-a891-90d97603c5c9' class='anno-94c17492-3c9c-4b16-a891-90d97603c5c9' data-letter-spacing='0.1180327868852459'>DELLA</span>",
                "language": "en"
            },
            "on": {
                "full": "https://readux.io/iiif/v2/t1114/canvas/t1114_00000119.jpg",
                "@type": "oa:SpecificResource",
                "within": {
                    "@id": "https://readux.io/iiif/v2/t1114/manifest",
                    "@type": "sc:Manifest"
                },
                "selector": {
                    "@type": "oa:FragmentSelector",
                    "value": "xywh=2694,4371,305,80",
                    "item": {
                        "@type": "oa:FragmentSelector"
                    }
                }
            },
            "stylesheet": {
                "type": "CssStylesheet",
                "value": ".anno-94c17492-3c9c-4b16-a891-90d97603c5c9: { height: 80px; width: 305px; font-size: 50.0px; letter-spacing: 36.0px;}"
            }
        },
        {
            "@context": "http://iiif.io/api/presentation/2/context.json",
            "@id": "b81f454b-db1a-4ccf-b3b2-7466d8d6a687",
            "@type": "oa:Annotation",
            "motivation": "sc:painting",
            "annotatedBy": {
                "name": "OCR"
            },
            "resource": {
                "@type": "cnt:ContentAsText",
                "format": "text/html",
                "chars": "<span id='b81f454b-db1a-4ccf-b3b2-7466d8d6a687' class='anno-b81f454b-db1a-4ccf-b3b2-7466d8d6a687' data-letter-spacing='0.08832694151486097'>FONTANA</span>",
                "language": "en"
            },
            "on": {
                "full": "https://readux.io/iiif/v2/t1114/canvas/t1114_00000119.jpg",
                "@type": "oa:SpecificResource",
                "within": {
                    "@id": "https://readux.io/iiif/v2/t1114/manifest",
                    "@type": "sc:Manifest"
                },
                "selector": {
                    "@type": "oa:FragmentSelector",
                    "value": "xywh=3075,4367,447,78",
                    "item": {
                        "@type": "oa:FragmentSelector"
                    }
                }
            },
            "stylesheet": {
                "type": "CssStylesheet",
                "value": ".anno-b81f454b-db1a-4ccf-b3b2-7466d8d6a687: { height: 78px; width: 447px; font-size: 48.75px; letter-spacing: 39.482142857142854px;}"
            }
        },
        {
            "@context": "http://iiif.io/api/presentation/2/context.json",
            "@id": "533dc685-3ab5-4ecd-b97f-6933538bef5f",
            "@type": "oa:Annotation",
            "motivation": "sc:painting",
            "annotatedBy": {
                "name": "OCR"
            },
            "resource": {
                "@type": "cnt:ContentAsText",
                "format": "text/html",
                "chars": "<span id='533dc685-3ab5-4ecd-b97f-6933538bef5f' class='anno-533dc685-3ab5-4ecd-b97f-6933538bef5f' data-letter-spacing='0.1311619718309859'>SVLA</span>",
                "language": "en"
            },
            "on": {
                "full": "https://readux.io/iiif/v2/t1114/canvas/t1114_00000119.jpg",
                "@type": "oa:SpecificResource",
                "within": {
                    "@id": "https://readux.io/iiif/v2/t1114/manifest",
                    "@type": "sc:Manifest"
                },
                "selector": {
                    "@type": "oa:FragmentSelector",
                    "value": "xywh=3598,4362,213,81",
                    "item": {
                        "@type": "oa:FragmentSelector"
                    }
                }
            },
            "stylesheet": {
                "type": "CssStylesheet",
                "value": ".anno-533dc685-3ab5-4ecd-b97f-6933538bef5f: { height: 81px; width: 213px; font-size: 50.625px; letter-spacing: 27.9375px;}"
            }
        },
        {
            "@context": "http://iiif.io/api/presentation/2/context.json",
            "@id": "0e650717-22b6-4462-9f12-af45a6b9a44d",
            "@type": "oa:Annotation",
            "motivation": "sc:painting",
            "annotatedBy": {
                "name": "OCR"
            },
            "resource": {
                "@type": "cnt:ContentAsText",
                "format": "text/html",
                "chars": "<span id='0e650717-22b6-4462-9f12-af45a6b9a44d' class='anno-0e650717-22b6-4462-9f12-af45a6b9a44d' data-letter-spacing='0.13898026315789475'>RVPE</span>",
                "language": "en"
            },
            "on": {
                "full": "https://readux.io/iiif/v2/t1114/canvas/t1114_00000119.jpg",
                "@type": "oa:SpecificResource",
                "within": {
                    "@id": "https://readux.io/iiif/v2/t1114/manifest",
                    "@type": "sc:Manifest"
                },
                "selector": {
                    "@type": "oa:FragmentSelector",
                    "value": "xywh=3888,4359,228,81",
                    "item": {
                        "@type": "oa:FragmentSelector"
                    }
                }
            },
            "stylesheet": {
                "type": "CssStylesheet",
                "value": ".anno-0e650717-22b6-4462-9f12-af45a6b9a44d: { height: 81px; width: 228px; font-size: 50.625px; letter-spacing: 31.6875px;}"
            }
        },
        {
            "@context": "http://iiif.io/api/presentation/2/context.json",
            "@id": "2fe40b9c-9330-458f-b0e9-b74e9e0d4292",
            "@type": "oa:Annotation",
            "motivation": "sc:painting",
            "annotatedBy": {
                "name": "OCR"
            },
            "resource": {
                "@type": "cnt:ContentAsText",
                "format": "text/html",
                "chars": "<span id='2fe40b9c-9330-458f-b0e9-b74e9e0d4292' class='anno-2fe40b9c-9330-458f-b0e9-b74e9e0d4292' data-letter-spacing='0.06341052402696239'>SVPERIORE</span>",
                "language": "en"
            },
            "on": {
                "full": "https://readux.io/iiif/v2/t1114/canvas/t1114_00000119.jpg",
                "@type": "oa:SpecificResource",
                "within": {
                    "@id": "https://readux.io/iiif/v2/t1114/manifest",
                    "@type": "sc:Manifest"
                },
                "selector": {
                    "@type": "oa:FragmentSelector",
                    "value": "xywh=4193,4356,511,78",
                    "item": {
                        "@type": "oa:FragmentSelector"
                    }
                }
            },
            "stylesheet": {
                "type": "CssStylesheet",
                "value": ".anno-2fe40b9c-9330-458f-b0e9-b74e9e0d4292: { height: 78px; width: 511px; font-size: 48.75px; letter-spacing: 32.40277777777778px;}"
            }
        },
        {
            "@context": "http://iiif.io/api/presentation/2/context.json",
            "@id": "fdccc1ec-2b8e-4f40-ad97-47cff922ba7f",
            "@type": "oa:Annotation",
            "motivation": "sc:painting",
            "annotatedBy": {
                "name": "OCR"
            },
            "resource": {
                "@type": "cnt:ContentAsText",
                "format": "text/html",
                "chars": "<span id='fdccc1ec-2b8e-4f40-ad97-47cff922ba7f' class='anno-fdccc1ec-2b8e-4f40-ad97-47cff922ba7f' data-letter-spacing='0.19425366300366298'>NEL</span>",
                "language": "en"
            },
            "on": {
                "full": "https://readux.io/iiif/v2/t1114/canvas/t1114_00000119.jpg",
                "@type": "oa:SpecificResource",
                "within": {
                    "@id": "https://readux.io/iiif/v2/t1114/manifest",
                    "@type": "sc:Manifest"
                },
                "selector": {
                    "@type": "oa:FragmentSelector",
                    "value": "xywh=4765,4351,182,81",
                    "item": {
                        "@type": "oa:FragmentSelector"
                    }
                }
            },
            "stylesheet": {
                "type": "CssStylesheet",
                "value": ".anno-fdccc1ec-2b8e-4f40-ad97-47cff922ba7f: { height: 81px; width: 182px; font-size: 50.625px; letter-spacing: 35.354166666666664px;}"
            }
        },
        {
            "@context": "http://iiif.io/api/presentation/2/context.json",
            "@id": "273ed81d-84c9-4f63-9a11-6ce7b24f844a",
            "@type": "oa:Annotation",
            "motivation": "sc:painting",
            "annotatedBy": {
                "name": "OCR"
            },
            "resource": {
                "@type": "cnt:ContentAsText",
                "format": "text/html",
                "chars": "<span id='273ed81d-84c9-4f63-9a11-6ce7b24f844a' class='anno-273ed81d-84c9-4f63-9a11-6ce7b24f844a' data-letter-spacing='0.09779900332225915'>SECONDO</span>",
                "language": "en"
            },
            "on": {
                "full": "https://readux.io/iiif/v2/t1114/canvas/t1114_00000119.jpg",
                "@type": "oa:SpecificResource",
                "within": {
                    "@id": "https://readux.io/iiif/v2/t1114/manifest",
                    "@type": "sc:Manifest"
                },
                "selector": {
                    "@type": "oa:FragmentSelector",
                    "value": "xywh=5059,4356,430,62",
                    "item": {
                        "@type": "oa:FragmentSelector"
                    }
                }
            },
            "stylesheet": {
                "type": "CssStylesheet",
                "value": ".anno-273ed81d-84c9-4f63-9a11-6ce7b24f844a: { height: 62px; width: 430px; font-size: 38.75px; letter-spacing: 42.05357142857143px;}"
            }
        },
        {
            "@context": "http://iiif.io/api/presentation/2/context.json",
            "@id": "e18f3a97-439c-4b32-9b1d-443bd5daf617",
            "@type": "oa:Annotation",
            "motivation": "sc:painting",
            "annotatedBy": {
                "name": "OCR"
            },
            "resource": {
                "@type": "cnt:ContentAsText",
                "format": "text/html",
                "chars": "<span id='e18f3a97-439c-4b32-9b1d-443bd5daf617' class='anno-e18f3a97-439c-4b32-9b1d-443bd5daf617' data-letter-spacing='0.121875'>PIANO</span>",
                "language": "en"
            },
            "on": {
                "full": "https://readux.io/iiif/v2/t1114/canvas/t1114_00000119.jpg",
                "@type": "oa:SpecificResource",
                "within": {
                    "@id": "https://readux.io/iiif/v2/t1114/manifest",
                    "@type": "sc:Manifest"
                },
                "selector": {
                    "@type": "oa:FragmentSelector",
                    "value": "xywh=5597,4352,252,63",
                    "item": {
                        "@type": "oa:FragmentSelector"
                    }
                }
            },
            "stylesheet": {
                "type": "CssStylesheet",
                "value": ".anno-e18f3a97-439c-4b32-9b1d-443bd5daf617: { height: 63px; width: 252px; font-size: 39.375px; letter-spacing: 30.7125px;}"
            }
        },
        {
            "@context": "http://iiif.io/api/presentation/2/context.json",
            "@id": "00ed1471-6225-4c14-b30d-1f02f50bd389",
            "@type": "oa:Annotation",
            "motivation": "sc:painting",
            "annotatedBy": {
                "name": "OCR"
            },
            "resource": {
                "@type": "cnt:ContentAsText",
                "format": "text/html",
                "chars": "<span id='00ed1471-6225-4c14-b30d-1f02f50bd389' class='anno-00ed1471-6225-4c14-b30d-1f02f50bd389' data-letter-spacing='0.15132783882783885'>Gio</span>",
                "language": "en"
            },
            "on": {
                "full": "https://readux.io/iiif/v2/t1114/canvas/t1114_00000119.jpg",
                "@type": "oa:SpecificResource",
                "within": {
                    "@id": "https://readux.io/iiif/v2/t1114/manifest",
                    "@type": "sc:Manifest"
                },
                "selector": {
                    "@type": "oa:FragmentSelector",
                    "value": "xywh=1116,4464,91,53",
                    "item": {
                        "@type": "oa:FragmentSelector"
                    }
                }
            },
            "stylesheet": {
                "type": "CssStylesheet",
                "value": ".anno-00ed1471-6225-4c14-b30d-1f02f50bd389: { height: 53px; width: 91px; font-size: 33.125px; letter-spacing: 13.770833333333334px;}"
            }
        },
        {
            "@context": "http://iiif.io/api/presentation/2/context.json",
            "@id": "dec22ee9-721b-4659-8aa3-11367f1a4fb1",
            "@type": "oa:Annotation",
            "motivation": "sc:painting",
            "annotatedBy": {
                "name": "OCR"
            },
            "resource": {
                "@type": "cnt:ContentAsText",
                "format": "text/html",
                "chars": "<span id='dec22ee9-721b-4659-8aa3-11367f1a4fb1' class='anno-dec22ee9-721b-4659-8aa3-11367f1a4fb1' data-letter-spacing='0.04763454861111111'>Francesco</span>",
                "language": "en"
            },
            "on": {
                "full": "https://readux.io/iiif/v2/t1114/canvas/t1114_00000119.jpg",
                "@type": "oa:SpecificResource",
                "within": {
                    "@id": "https://readux.io/iiif/v2/t1114/manifest",
                    "@type": "sc:Manifest"
                },
                "selector": {
                    "@type": "oa:FragmentSelector",
                    "value": "xywh=1223,4462,256,52",
                    "item": {
                        "@type": "oa:FragmentSelector"
                    }
                }
            },
            "stylesheet": {
                "type": "CssStylesheet",
                "value": ".anno-dec22ee9-721b-4659-8aa3-11367f1a4fb1: { height: 52px; width: 256px; font-size: 32.5px; letter-spacing: 12.194444444444445px;}"
            }
        },
        {
            "@context": "http://iiif.io/api/presentation/2/context.json",
            "@id": "02af0e8f-6d8b-4a66-91ae-f86397b28d9b",
            "@type": "oa:Annotation",
            "motivation": "sc:painting",
            "annotatedBy": {
                "name": "OCR"
            },
            "resource": {
                "@type": "cnt:ContentAsText",
                "format": "text/html",
                "chars": "<span id='02af0e8f-6d8b-4a66-91ae-f86397b28d9b' class='anno-02af0e8f-6d8b-4a66-91ae-f86397b28d9b' data-letter-spacing='0.05096960167714885'>Venturini</span>",
                "language": "en"
            },
            "on": {
                "full": "https://readux.io/iiif/v2/t1114/canvas/t1114_00000119.jpg",
                "@type": "oa:SpecificResource",
                "within": {
                    "@id": "https://readux.io/iiif/v2/t1114/manifest",
                    "@type": "sc:Manifest"
                },
                "selector": {
                    "@type": "oa:FragmentSelector",
                    "value": "xywh=1496,4461,265,51",
                    "item": {
                        "@type": "oa:FragmentSelector"
                    }
                }
            },
            "stylesheet": {
                "type": "CssStylesheet",
                "value": ".anno-02af0e8f-6d8b-4a66-91ae-f86397b28d9b: { height: 51px; width: 265px; font-size: 31.875px; letter-spacing: 13.506944444444445px;}"
            }
        },
        {
            "@context": "http://iiif.io/api/presentation/2/context.json",
            "@id": "0f8631ee-cf03-4ea1-9250-faccdd7c6e24",
            "@type": "oa:Annotation",
            "motivation": "sc:painting",
            "annotatedBy": {
                "name": "OCR"
            },
            "resource": {
                "@type": "cnt:ContentAsText",
                "format": "text/html",
                "chars": "<span id='0f8631ee-cf03-4ea1-9250-faccdd7c6e24' class='anno-0f8631ee-cf03-4ea1-9250-faccdd7c6e24' data-letter-spacing='0.13988095238095238'>del</span>",
                "language": "en"
            },
            "on": {
                "full": "https://readux.io/iiif/v2/t1114/canvas/t1114_00000119.jpg",
                "@type": "oa:SpecificResource",
                "within": {
                    "@id": "https://readux.io/iiif/v2/t1114/manifest",
                    "@type": "sc:Manifest"
                },
                "selector": {
                    "@type": "oa:FragmentSelector",
                    "value": "xywh=1786,4459,84,52",
                    "item": {
                        "@type": "oa:FragmentSelector"
                    }
                }
            },
            "stylesheet": {
                "type": "CssStylesheet",
                "value": ".anno-0f8631ee-cf03-4ea1-9250-faccdd7c6e24: { height: 52px; width: 84px; font-size: 32.5px; letter-spacing: 11.75px;}"
            }
        },
        {
            "@context": "http://iiif.io/api/presentation/2/context.json",
            "@id": "de206e04-d082-411d-beae-ccc5ed08dddf",
            "@type": "oa:Annotation",
            "motivation": "sc:painting",
            "annotatedBy": {
                "name": "OCR"
            },
            "resource": {
                "@type": "cnt:ContentAsText",
                "format": "text/html",
                "chars": "<span id='de206e04-d082-411d-beae-ccc5ed08dddf' class='anno-de206e04-d082-411d-beae-ccc5ed08dddf' data-letter-spacing='-0.03515625'>:</span>",
                "language": "en"
            },
            "on": {
                "full": "https://readux.io/iiif/v2/t1114/canvas/t1114_00000119.jpg",
                "@type": "oa:SpecificResource",
                "within": {
                    "@id": "https://readux.io/iiif/v2/t1114/manifest",
                    "@type": "sc:Manifest"
                },
                "selector": {
                    "@type": "oa:FragmentSelector",
                    "value": "xywh=1875,4458,16,53",
                    "item": {
                        "@type": "oa:FragmentSelector"
                    }
                }
            },
            "stylesheet": {
                "type": "CssStylesheet",
                "value": ".anno-de206e04-d082-411d-beae-ccc5ed08dddf: { height: 53px; width: 16px; font-size: 33.125px; letter-spacing: -0.5625px;}"
            }
        },
        {
            "@context": "http://iiif.io/api/presentation/2/context.json",
            "@id": "f5baa80d-2a6d-432a-95f7-27e5cb493967",
            "@type": "oa:Annotation",
            "motivation": "sc:painting",
            "annotatedBy": {
                "name": "OCR"
            },
            "resource": {
                "@type": "cnt:ContentAsText",
                "format": "text/html",
                "chars": "<span id='f5baa80d-2a6d-432a-95f7-27e5cb493967' class='anno-f5baa80d-2a6d-432a-95f7-27e5cb493967' data-letter-spacing='0.12357954545454546'>et</span>",
                "language": "en"
            },
            "on": {
                "full": "https://readux.io/iiif/v2/t1114/canvas/t1114_00000119.jpg",
                "@type": "oa:SpecificResource",
                "within": {
                    "@id": "https://readux.io/iiif/v2/t1114/manifest",
                    "@type": "sc:Manifest"
                },
                "selector": {
                    "@type": "oa:FragmentSelector",
                    "value": "xywh=1908,4458,44,53",
                    "item": {
                        "@type": "oa:FragmentSelector"
                    }
                }
            },
            "stylesheet": {
                "type": "CssStylesheet",
                "value": ".anno-f5baa80d-2a6d-432a-95f7-27e5cb493967: { height: 53px; width: 44px; font-size: 33.125px; letter-spacing: 5.4375px;}"
            }
        },
        {
            "@context": "http://iiif.io/api/presentation/2/context.json",
            "@id": "f9f49a2a-b633-4c45-a351-d32ce45dc83b",
            "@type": "oa:Annotation",
            "motivation": "sc:painting",
            "annotatedBy": {
                "name": "OCR"
            },
            "resource": {
                "@type": "cnt:ContentAsText",
                "format": "text/html",
                "chars": "<span id='f9f49a2a-b633-4c45-a351-d32ce45dc83b' class='anno-f9f49a2a-b633-4c45-a351-d32ce45dc83b' data-letter-spacing='0.004807692307692308'>inic</span>",
                "language": "en"
            },
            "on": {
                "full": "https://readux.io/iiif/v2/t1114/canvas/t1114_00000119.jpg",
                "@type": "oa:SpecificResource",
                "within": {
                    "@id": "https://readux.io/iiif/v2/t1114/manifest",
                    "@type": "sc:Manifest"
                },
                "selector": {
                    "@type": "oa:FragmentSelector",
                    "value": "xywh=1996,4458,65,51",
                    "item": {
                        "@type": "oa:FragmentSelector"
                    }
                }
            },
            "stylesheet": {
                "type": "CssStylesheet",
                "value": ".anno-f9f49a2a-b633-4c45-a351-d32ce45dc83b: { height: 51px; width: 65px; font-size: 31.875px; letter-spacing: 0.3125px;}"
            }
        },
        {
            "@context": "http://iiif.io/api/presentation/2/context.json",
            "@id": "6e584d4d-9cc6-46b8-a73e-b50ff9c28944",
            "@type": "oa:Annotation",
            "motivation": "sc:painting",
            "annotatedBy": {
                "name": "OCR"
            },
            "resource": {
                "@type": "cnt:ContentAsText",
                "format": "text/html",
                "chars": "<span id='6e584d4d-9cc6-46b8-a73e-b50ff9c28944' class='anno-6e584d4d-9cc6-46b8-a73e-b50ff9c28944' data-letter-spacing='-0.10416666666666667'>.</span>",
                "language": "en"
            },
            "on": {
                "full": "https://readux.io/iiif/v2/t1114/canvas/t1114_00000119.jpg",
                "@type": "oa:SpecificResource",
                "within": {
                    "@id": "https://readux.io/iiif/v2/t1114/manifest",
                    "@type": "sc:Manifest"
                },
                "selector": {
                    "@type": "oa:FragmentSelector",
                    "value": "xywh=2083,4456,15,53",
                    "item": {
                        "@type": "oa:FragmentSelector"
                    }
                }
            },
            "stylesheet": {
                "type": "CssStylesheet",
                "value": ".anno-6e584d4d-9cc6-46b8-a73e-b50ff9c28944: { height: 53px; width: 15px; font-size: 33.125px; letter-spacing: -1.5625px;}"
            }
        },
        {
            "@context": "http://iiif.io/api/presentation/2/context.json",
            "@id": "3b1b39af-3854-439a-83c4-205ccc6e9604",
            "@type": "oa:Annotation",
            "motivation": "sc:painting",
            "annotatedBy": {
                "name": "OCR"
            },
            "resource": {
                "@type": "cnt:ContentAsText",
                "format": "text/html",
                "chars": "<span id='3b1b39af-3854-439a-83c4-205ccc6e9604' class='anno-3b1b39af-3854-439a-83c4-205ccc6e9604' data-letter-spacing='0.02987938596491228'>Architettura</span>",
                "language": "en"
            },
            "on": {
                "full": "https://readux.io/iiif/v2/t1114/canvas/t1114_00000119.jpg",
                "@type": "oa:SpecificResource",
                "within": {
                    "@id": "https://readux.io/iiif/v2/t1114/manifest",
                    "@type": "sc:Manifest"
                },
                "selector": {
                    "@type": "oa:FragmentSelector",
                    "value": "xywh=3073,4448,380,65",
                    "item": {
                        "@type": "oa:FragmentSelector"
                    }
                }
            },
            "stylesheet": {
                "type": "CssStylesheet",
                "value": ".anno-3b1b39af-3854-439a-83c4-205ccc6e9604: { height: 65px; width: 380px; font-size: 40.625px; letter-spacing: 11.354166666666666px;}"
            }
        },
        {
            "@context": "http://iiif.io/api/presentation/2/context.json",
            "@id": "f90f4148-2731-4c6c-ac83-b0a491a45521",
            "@type": "oa:Annotation",
            "motivation": "sc:painting",
            "annotatedBy": {
                "name": "OCR"
            },
            "resource": {
                "@type": "cnt:ContentAsText",
                "format": "text/html",
                "chars": "<span id='f90f4148-2731-4c6c-ac83-b0a491a45521' class='anno-f90f4148-2731-4c6c-ac83-b0a491a45521' data-letter-spacing='0.07720588235294118'>di</span>",
                "language": "en"
            },
            "on": {
                "full": "https://readux.io/iiif/v2/t1114/canvas/t1114_00000119.jpg",
                "@type": "oa:SpecificResource",
                "within": {
                    "@id": "https://readux.io/iiif/v2/t1114/manifest",
                    "@type": "sc:Manifest"
                },
                "selector": {
                    "@type": "oa:FragmentSelector",
                    "value": "xywh=3530,4443,51,69",
                    "item": {
                        "@type": "oa:FragmentSelector"
                    }
                }
            },
            "stylesheet": {
                "type": "CssStylesheet",
                "value": ".anno-f90f4148-2731-4c6c-ac83-b0a491a45521: { height: 69px; width: 51px; font-size: 43.125px; letter-spacing: 3.9375px;}"
            }
        },
        {
            "@context": "http://iiif.io/api/presentation/2/context.json",
            "@id": "1850c292-65e1-40a3-a76f-23e59333bcb1",
            "@type": "oa:Annotation",
            "motivation": "sc:painting",
            "annotatedBy": {
                "name": "OCR"
            },
            "resource": {
                "@type": "cnt:ContentAsText",
                "format": "text/html",
                "chars": "<span id='1850c292-65e1-40a3-a76f-23e59333bcb1' class='anno-1850c292-65e1-40a3-a76f-23e59333bcb1' data-letter-spacing='0.058141447368421056'>Carlo</span>",
                "language": "en"
            },
            "on": {
                "full": "https://readux.io/iiif/v2/t1114/canvas/t1114_00000119.jpg",
                "@type": "oa:SpecificResource",
                "within": {
                    "@id": "https://readux.io/iiif/v2/t1114/manifest",
                    "@type": "sc:Manifest"
                },
                "selector": {
                    "@type": "oa:FragmentSelector",
                    "value": "xywh=3623,4442,152,69",
                    "item": {
                        "@type": "oa:FragmentSelector"
                    }
                }
            },
            "stylesheet": {
                "type": "CssStylesheet",
                "value": ".anno-1850c292-65e1-40a3-a76f-23e59333bcb1: { height: 69px; width: 152px; font-size: 43.125px; letter-spacing: 8.8375px;}"
            }
        },
        {
            "@context": "http://iiif.io/api/presentation/2/context.json",
            "@id": "2c2d9538-afb7-44e7-9f1f-62b9464ef330",
            "@type": "oa:Annotation",
            "motivation": "sc:painting",
            "annotatedBy": {
                "name": "OCR"
            },
            "resource": {
                "@type": "cnt:ContentAsText",
                "format": "text/html",
                "chars": "<span id='2c2d9538-afb7-44e7-9f1f-62b9464ef330' class='anno-2c2d9538-afb7-44e7-9f1f-62b9464ef330' data-letter-spacing='0.07246465138956606'>maderno</span>",
                "language": "en"
            },
            "on": {
                "full": "https://readux.io/iiif/v2/t1114/canvas/t1114_00000119.jpg",
                "@type": "oa:SpecificResource",
                "within": {
                    "@id": "https://readux.io/iiif/v2/t1114/manifest",
                    "@type": "sc:Manifest"
                },
                "selector": {
                    "@type": "oa:FragmentSelector",
                    "value": "xywh=3836,4440,293,66",
                    "item": {
                        "@type": "oa:FragmentSelector"
                    }
                }
            },
            "stylesheet": {
                "type": "CssStylesheet",
                "value": ".anno-2c2d9538-afb7-44e7-9f1f-62b9464ef330: { height: 66px; width: 293px; font-size: 41.25px; letter-spacing: 21.232142857142858px;}"
            }
        },
        {
            "@context": "http://iiif.io/api/presentation/2/context.json",
            "@id": "ef20efc2-238b-4e41-b0dd-d2b623383d79",
            "@type": "oa:Annotation",
            "motivation": "sc:painting",
            "annotatedBy": {
                "name": "OCR"
            },
            "resource": {
                "@type": "cnt:ContentAsText",
                "format": "text/html",
                "chars": "<span id='ef20efc2-238b-4e41-b0dd-d2b623383d79' class='anno-ef20efc2-238b-4e41-b0dd-d2b623383d79' data-letter-spacing='-0.078125'>.</span>",
                "language": "en"
            },
            "on": {
                "full": "https://readux.io/iiif/v2/t1114/canvas/t1114_00000119.jpg",
                "@type": "oa:SpecificResource",
                "within": {
                    "@id": "https://readux.io/iiif/v2/t1114/manifest",
                    "@type": "sc:Manifest"
                },
                "selector": {
                    "@type": "oa:FragmentSelector",
                    "value": "xywh=4137,4437,20,69",
                    "item": {
                        "@type": "oa:FragmentSelector"
                    }
                }
            },
            "stylesheet": {
                "type": "CssStylesheet",
                "value": ".anno-ef20efc2-238b-4e41-b0dd-d2b623383d79: { height: 69px; width: 20px; font-size: 43.125px; letter-spacing: -1.5625px;}"
            }
        },
        {
            "@context": "http://iiif.io/api/presentation/2/context.json",
            "@id": "b3ad693b-1b93-4811-85e2-b0c0f5e84d95",
            "@type": "oa:Annotation",
            "motivation": "sc:painting",
            "annotatedBy": {
                "name": "OCR"
            },
            "resource": {
                "@type": "cnt:ContentAsText",
                "format": "text/html",
                "chars": "<span id='b3ad693b-1b93-4811-85e2-b0c0f5e84d95' class='anno-b3ad693b-1b93-4811-85e2-b0c0f5e84d95' data-letter-spacing='0.06607142857142857'>G.Iac</span>",
                "language": "en"
            },
            "on": {
                "full": "https://readux.io/iiif/v2/t1114/canvas/t1114_00000119.jpg",
                "@type": "oa:SpecificResource",
                "within": {
                    "@id": "https://readux.io/iiif/v2/t1114/manifest",
                    "@type": "sc:Manifest"
                },
                "selector": {
                    "@type": "oa:FragmentSelector",
                    "value": "xywh=4547,4449,133,57",
                    "item": {
                        "@type": "oa:FragmentSelector"
                    }
                }
            },
            "stylesheet": {
                "type": "CssStylesheet",
                "value": ".anno-b3ad693b-1b93-4811-85e2-b0c0f5e84d95: { height: 57px; width: 133px; font-size: 35.625px; letter-spacing: 8.7875px;}"
            }
        },
        {
            "@context": "http://iiif.io/api/presentation/2/context.json",
            "@id": "981bb242-d1eb-463f-9049-b8f5cbf85363",
            "@type": "oa:Annotation",
            "motivation": "sc:painting",
            "annotatedBy": {
                "name": "OCR"
            },
            "resource": {
                "@type": "cnt:ContentAsText",
                "format": "text/html",
                "chars": "<span id='981bb242-d1eb-463f-9049-b8f5cbf85363' class='anno-981bb242-d1eb-463f-9049-b8f5cbf85363' data-letter-spacing='-0.0661764705882353'>.</span>",
                "language": "en"
            },
            "on": {
                "full": "https://readux.io/iiif/v2/t1114/canvas/t1114_00000119.jpg",
                "@type": "oa:SpecificResource",
                "within": {
                    "@id": "https://readux.io/iiif/v2/t1114/manifest",
                    "@type": "sc:Manifest"
                },
                "selector": {
                    "@type": "oa:FragmentSelector",
                    "value": "xywh=4687,4448,17,58",
                    "item": {
                        "@type": "oa:FragmentSelector"
                    }
                }
            },
            "stylesheet": {
                "type": "CssStylesheet",
                "value": ".anno-981bb242-d1eb-463f-9049-b8f5cbf85363: { height: 58px; width: 17px; font-size: 36.25px; letter-spacing: -1.125px;}"
            }
        },
        {
            "@context": "http://iiif.io/api/presentation/2/context.json",
            "@id": "dab7b2c3-d829-4cca-b565-9a0bd0a99538",
            "@type": "oa:Annotation",
            "motivation": "sc:painting",
            "annotatedBy": {
                "name": "OCR"
            },
            "resource": {
                "@type": "cnt:ContentAsText",
                "format": "text/html",
                "chars": "<span id='dab7b2c3-d829-4cca-b565-9a0bd0a99538' class='anno-dab7b2c3-d829-4cca-b565-9a0bd0a99538' data-letter-spacing='0.007942708333333333'>Ro\u017f\u017fi</span>",
                "language": "en"
            },
            "on": {
                "full": "https://readux.io/iiif/v2/t1114/canvas/t1114_00000119.jpg",
                "@type": "oa:SpecificResource",
                "within": {
                    "@id": "https://readux.io/iiif/v2/t1114/manifest",
                    "@type": "sc:Manifest"
                },
                "selector": {
                    "@type": "oa:FragmentSelector",
                    "value": "xywh=4706,4446,96,59",
                    "item": {
                        "@type": "oa:FragmentSelector"
                    }
                }
            },
            "stylesheet": {
                "type": "CssStylesheet",
                "value": ".anno-dab7b2c3-d829-4cca-b565-9a0bd0a99538: { height: 59px; width: 96px; font-size: 36.875px; letter-spacing: 0.7625px;}"
            }
        },
        {
            "@context": "http://iiif.io/api/presentation/2/context.json",
            "@id": "b82d1d01-2454-43a9-8353-39ca95f60aab",
            "@type": "oa:Annotation",
            "motivation": "sc:painting",
            "annotatedBy": {
                "name": "OCR"
            },
            "resource": {
                "@type": "cnt:ContentAsText",
                "format": "text/html",
                "chars": "<span id='b82d1d01-2454-43a9-8353-39ca95f60aab' class='anno-b82d1d01-2454-43a9-8353-39ca95f60aab' data-letter-spacing='-0.07459677419354839'>le</span>",
                "language": "en"
            },
            "on": {
                "full": "https://readux.io/iiif/v2/t1114/canvas/t1114_00000119.jpg",
                "@type": "oa:SpecificResource",
                "within": {
                    "@id": "https://readux.io/iiif/v2/t1114/manifest",
                    "@type": "sc:Manifest"
                },
                "selector": {
                    "@type": "oa:FragmentSelector",
                    "value": "xywh=4827,4446,31,57",
                    "item": {
                        "@type": "oa:FragmentSelector"
                    }
                }
            },
            "stylesheet": {
                "type": "CssStylesheet",
                "value": ".anno-b82d1d01-2454-43a9-8353-39ca95f60aab: { height: 57px; width: 31px; font-size: 35.625px; letter-spacing: -2.3125px;}"
            }
        },
        {
            "@context": "http://iiif.io/api/presentation/2/context.json",
            "@id": "c2371ead-e1d6-44fe-817a-8830852eed8c",
            "@type": "oa:Annotation",
            "motivation": "sc:painting",
            "annotatedBy": {
                "name": "OCR"
            },
            "resource": {
                "@type": "cnt:ContentAsText",
                "format": "text/html",
                "chars": "<span id='c2371ead-e1d6-44fe-817a-8830852eed8c' class='anno-c2371ead-e1d6-44fe-817a-8830852eed8c' data-letter-spacing='0.06000499001996008'>stampa</span>",
                "language": "en"
            },
            "on": {
                "full": "https://readux.io/iiif/v2/t1114/canvas/t1114_00000119.jpg",
                "@type": "oa:SpecificResource",
                "within": {
                    "@id": "https://readux.io/iiif/v2/t1114/manifest",
                    "@type": "sc:Manifest"
                },
                "selector": {
                    "@type": "oa:FragmentSelector",
                    "value": "xywh=4878,4445,167,57",
                    "item": {
                        "@type": "oa:FragmentSelector"
                    }
                }
            },
            "stylesheet": {
                "type": "CssStylesheet",
                "value": ".anno-c2371ead-e1d6-44fe-817a-8830852eed8c: { height: 57px; width: 167px; font-size: 35.625px; letter-spacing: 10.020833333333334px;}"
            }
        },
        {
            "@context": "http://iiif.io/api/presentation/2/context.json",
            "@id": "fb33b1d2-2237-4c6e-a340-a2dc44eaaa3c",
            "@type": "oa:Annotation",
            "motivation": "sc:painting",
            "annotatedBy": {
                "name": "OCR"
            },
            "resource": {
                "@type": "cnt:ContentAsText",
                "format": "text/html",
                "chars": "<span id='fb33b1d2-2237-4c6e-a340-a2dc44eaaa3c' class='anno-fb33b1d2-2237-4c6e-a340-a2dc44eaaa3c' data-letter-spacing='-0.32386363636363635'>in</span>",
                "language": "en"
            },
            "on": {
                "full": "https://readux.io/iiif/v2/t1114/canvas/t1114_00000119.jpg",
                "@type": "oa:SpecificResource",
                "within": {
                    "@id": "https://readux.io/iiif/v2/t1114/manifest",
                    "@type": "sc:Manifest"
                },
                "selector": {
                    "@type": "oa:FragmentSelector",
                    "value": "xywh=5082,4442,22,58",
                    "item": {
                        "@type": "oa:FragmentSelector"
                    }
                }
            },
            "stylesheet": {
                "type": "CssStylesheet",
                "value": ".anno-fb33b1d2-2237-4c6e-a340-a2dc44eaaa3c: { height: 58px; width: 22px; font-size: 36.25px; letter-spacing: -7.125px;}"
            }
        },
        {
            "@context": "http://iiif.io/api/presentation/2/context.json",
            "@id": "4ecc9831-1442-45e8-a61b-4d9cf01bea7e",
            "@type": "oa:Annotation",
            "motivation": "sc:painting",
            "annotatedBy": {
                "name": "OCR"
            },
            "resource": {
                "@type": "cnt:ContentAsText",
                "format": "text/html",
                "chars": "<span id='4ecc9831-1442-45e8-a61b-4d9cf01bea7e' class='anno-4ecc9831-1442-45e8-a61b-4d9cf01bea7e' data-letter-spacing='0.1328125'>Roma</span>",
                "language": "en"
            },
            "on": {
                "full": "https://readux.io/iiif/v2/t1114/canvas/t1114_00000119.jpg",
                "@type": "oa:SpecificResource",
                "within": {
                    "@id": "https://readux.io/iiif/v2/t1114/manifest",
                    "@type": "sc:Manifest"
                },
                "selector": {
                    "@type": "oa:FragmentSelector",
                    "value": "xywh=5130,4442,152,57",
                    "item": {
                        "@type": "oa:FragmentSelector"
                    }
                }
            },
            "stylesheet": {
                "type": "CssStylesheet",
                "value": ".anno-4ecc9831-1442-45e8-a61b-4d9cf01bea7e: { height: 57px; width: 152px; font-size: 35.625px; letter-spacing: 20.1875px;}"
            }
        },
        {
            "@context": "http://iiif.io/api/presentation/2/context.json",
            "@id": "e719650a-5ef6-4f8b-99bd-ac7d4a4b85f5",
            "@type": "oa:Annotation",
            "motivation": "sc:painting",
            "annotatedBy": {
                "name": "OCR"
            },
            "resource": {
                "@type": "cnt:ContentAsText",
                "format": "text/html",
                "chars": "<span id='e719650a-5ef6-4f8b-99bd-ac7d4a4b85f5' class='anno-e719650a-5ef6-4f8b-99bd-ac7d4a4b85f5' data-letter-spacing='0.0234375'>alla</span>",
                "language": "en"
            },
            "on": {
                "full": "https://readux.io/iiif/v2/t1114/canvas/t1114_00000119.jpg",
                "@type": "oa:SpecificResource",
                "within": {
                    "@id": "https://readux.io/iiif/v2/t1114/manifest",
                    "@type": "sc:Manifest"
                },
                "selector": {
                    "@type": "oa:FragmentSelector",
                    "value": "xywh=5318,4439,80,58",
                    "item": {
                        "@type": "oa:FragmentSelector"
                    }
                }
            },
            "stylesheet": {
                "type": "CssStylesheet",
                "value": ".anno-e719650a-5ef6-4f8b-99bd-ac7d4a4b85f5: { height: 58px; width: 80px; font-size: 36.25px; letter-spacing: 1.875px;}"
            }
        },
        {
            "@context": "http://iiif.io/api/presentation/2/context.json",
            "@id": "deb479e8-6571-47e1-9f4c-ba3bfc271b68",
            "@type": "oa:Annotation",
            "motivation": "sc:painting",
            "annotatedBy": {
                "name": "OCR"
            },
            "resource": {
                "@type": "cnt:ContentAsText",
                "format": "text/html",
                "chars": "<span id='deb479e8-6571-47e1-9f4c-ba3bfc271b68' class='anno-deb479e8-6571-47e1-9f4c-ba3bfc271b68' data-letter-spacing='0.09635416666666667'>pace</span>",
                "language": "en"
            },
            "on": {
                "full": "https://readux.io/iiif/v2/t1114/canvas/t1114_00000119.jpg",
                "@type": "oa:SpecificResource",
                "within": {
                    "@id": "https://readux.io/iiif/v2/t1114/manifest",
                    "@type": "sc:Manifest"
                },
                "selector": {
                    "@type": "oa:FragmentSelector",
                    "value": "xywh=5416,4437,120,59",
                    "item": {
                        "@type": "oa:FragmentSelector"
                    }
                }
            },
            "stylesheet": {
                "type": "CssStylesheet",
                "value": ".anno-deb479e8-6571-47e1-9f4c-ba3bfc271b68: { height: 59px; width: 120px; font-size: 36.875px; letter-spacing: 11.5625px;}"
            }
        },
        {
            "@context": "http://iiif.io/api/presentation/2/context.json",
            "@id": "1b8ffc6f-d598-4d7f-8e8a-e7c62b744867",
            "@type": "oa:Annotation",
            "motivation": "sc:painting",
            "annotatedBy": {
                "name": "OCR"
            },
            "resource": {
                "@type": "cnt:ContentAsText",
                "format": "text/html",
                "chars": "<span id='1b8ffc6f-d598-4d7f-8e8a-e7c62b744867' class='anno-1b8ffc6f-d598-4d7f-8e8a-e7c62b744867' data-letter-spacing='0.09794372294372294'>con</span>",
                "language": "en"
            },
            "on": {
                "full": "https://readux.io/iiif/v2/t1114/canvas/t1114_00000119.jpg",
                "@type": "oa:SpecificResource",
                "within": {
                    "@id": "https://readux.io/iiif/v2/t1114/manifest",
                    "@type": "sc:Manifest"
                },
                "selector": {
                    "@type": "oa:FragmentSelector",
                    "value": "xywh=5565,4436,77,58",
                    "item": {
                        "@type": "oa:FragmentSelector"
                    }
                }
            },
            "stylesheet": {
                "type": "CssStylesheet",
                "value": ".anno-1b8ffc6f-d598-4d7f-8e8a-e7c62b744867: { height: 58px; width: 77px; font-size: 36.25px; letter-spacing: 7.541666666666667px;}"
            }
        },
        {
            "@context": "http://iiif.io/api/presentation/2/context.json",
            "@id": "b6b680cb-333e-4eaa-b86e-d56620e46f62",
            "@type": "oa:Annotation",
            "motivation": "sc:painting",
            "annotatedBy": {
                "name": "OCR"
            },
            "resource": {
                "@type": "cnt:ContentAsText",
                "format": "text/html",
                "chars": "<span id='b6b680cb-333e-4eaa-b86e-d56620e46f62' class='anno-b6b680cb-333e-4eaa-b86e-d56620e46f62' data-letter-spacing='0.025152439024390245'>Priu</span>",
                "language": "en"
            },
            "on": {
                "full": "https://readux.io/iiif/v2/t1114/canvas/t1114_00000119.jpg",
                "@type": "oa:SpecificResource",
                "within": {
                    "@id": "https://readux.io/iiif/v2/t1114/manifest",
                    "@type": "sc:Manifest"
                },
                "selector": {
                    "@type": "oa:FragmentSelector",
                    "value": "xywh=5673,4434,82,59",
                    "item": {
                        "@type": "oa:FragmentSelector"
                    }
                }
            },
            "stylesheet": {
                "type": "CssStylesheet",
                "value": ".anno-b6b680cb-333e-4eaa-b86e-d56620e46f62: { height: 59px; width: 82px; font-size: 36.875px; letter-spacing: 2.0625px;}"
            }
        },
        {
            "@context": "http://iiif.io/api/presentation/2/context.json",
            "@id": "c95529c9-7bcf-4afb-b031-98b5de9a044a",
            "@type": "oa:Annotation",
            "motivation": "sc:painting",
            "annotatedBy": {
                "name": "OCR"
            },
            "resource": {
                "@type": "cnt:ContentAsText",
                "format": "text/html",
                "chars": "<span id='c95529c9-7bcf-4afb-b031-98b5de9a044a' class='anno-c95529c9-7bcf-4afb-b031-98b5de9a044a' data-letter-spacing='-0.08455882352941177'>.</span>",
                "language": "en"
            },
            "on": {
                "full": "https://readux.io/iiif/v2/t1114/canvas/t1114_00000119.jpg",
                "@type": "oa:SpecificResource",
                "within": {
                    "@id": "https://readux.io/iiif/v2/t1114/manifest",
                    "@type": "sc:Manifest"
                },
                "selector": {
                    "@type": "oa:FragmentSelector",
                    "value": "xywh=5772,4434,17,59",
                    "item": {
                        "@type": "oa:FragmentSelector"
                    }
                }
            },
            "stylesheet": {
                "type": "CssStylesheet",
                "value": ".anno-c95529c9-7bcf-4afb-b031-98b5de9a044a: { height: 59px; width: 17px; font-size: 36.875px; letter-spacing: -1.4375px;}"
            }
        },
        {
            "@context": "http://iiif.io/api/presentation/2/context.json",
            "@id": "4e61110c-fe54-4c44-9258-5426ca98575c",
            "@type": "oa:Annotation",
            "motivation": "sc:painting",
            "annotatedBy": {
                "name": "OCR"
            },
            "resource": {
                "@type": "cnt:ContentAsText",
                "format": "text/html",
                "chars": "<span id='4e61110c-fe54-4c44-9258-5426ca98575c' class='anno-4e61110c-fe54-4c44-9258-5426ca98575c' data-letter-spacing='0.06678921568627451'>del</span>",
                "language": "en"
            },
            "on": {
                "full": "https://readux.io/iiif/v2/t1114/canvas/t1114_00000119.jpg",
                "@type": "oa:SpecificResource",
                "within": {
                    "@id": "https://readux.io/iiif/v2/t1114/manifest",
                    "@type": "sc:Manifest"
                },
                "selector": {
                    "@type": "oa:FragmentSelector",
                    "value": "xywh=5800,4433,68,58",
                    "item": {
                        "@type": "oa:FragmentSelector"
                    }
                }
            },
            "stylesheet": {
                "type": "CssStylesheet",
                "value": ".anno-4e61110c-fe54-4c44-9258-5426ca98575c: { height: 58px; width: 68px; font-size: 36.25px; letter-spacing: 4.541666666666667px;}"
            }
        },
        {
            "@context": "http://iiif.io/api/presentation/2/context.json",
            "@id": "0a673f0e-c915-465c-8b2f-89ccd095465c",
            "@type": "oa:Annotation",
            "motivation": "sc:painting",
            "annotatedBy": {
                "name": "OCR"
            },
            "resource": {
                "@type": "cnt:ContentAsText",
                "format": "text/html",
                "chars": "<span id='0a673f0e-c915-465c-8b2f-89ccd095465c' class='anno-0a673f0e-c915-465c-8b2f-89ccd095465c' data-letter-spacing='0.08096590909090909'>S.</span>",
                "language": "en"
            },
            "on": {
                "full": "https://readux.io/iiif/v2/t1114/canvas/t1114_00000119.jpg",
                "@type": "oa:SpecificResource",
                "within": {
                    "@id": "https://readux.io/iiif/v2/t1114/manifest",
                    "@type": "sc:Manifest"
                },
                "selector": {
                    "@type": "oa:FragmentSelector",
                    "value": "xywh=5914,4431,44,59",
                    "item": {
                        "@type": "oa:FragmentSelector"
                    }
                }
            },
            "stylesheet": {
                "type": "CssStylesheet",
                "value": ".anno-0a673f0e-c915-465c-8b2f-89ccd095465c: { height: 59px; width: 44px; font-size: 36.875px; letter-spacing: 3.5625px;}"
            }
        },
        {
            "@context": "http://iiif.io/api/presentation/2/context.json",
            "@id": "307c3652-0ead-4469-90e4-d0ab3d9ff950",
            "@type": "oa:Annotation",
            "motivation": "sc:painting",
            "annotatedBy": {
                "name": "OCR"
            },
            "resource": {
                "@type": "cnt:ContentAsText",
                "format": "text/html",
                "chars": "<span id='307c3652-0ead-4469-90e4-d0ab3d9ff950' class='anno-307c3652-0ead-4469-90e4-d0ab3d9ff950' data-letter-spacing='0.07536764705882353'>Pont</span>",
                "language": "en"
            },
            "on": {
                "full": "https://readux.io/iiif/v2/t1114/canvas/t1114_00000119.jpg",
                "@type": "oa:SpecificResource",
                "within": {
                    "@id": "https://readux.io/iiif/v2/t1114/manifest",
                    "@type": "sc:Manifest"
                },
                "selector": {
                    "@type": "oa:FragmentSelector",
                    "value": "xywh=5973,4431,102,57",
                    "item": {
                        "@type": "oa:FragmentSelector"
                    }
                }
            },
            "stylesheet": {
                "type": "CssStylesheet",
                "value": ".anno-307c3652-0ead-4469-90e4-d0ab3d9ff950: { height: 57px; width: 102px; font-size: 35.625px; letter-spacing: 7.6875px;}"
            }
        },
        {
            "@context": "http://iiif.io/api/presentation/2/context.json",
            "@id": "c4be86d2-8947-4ec7-87d5-b5ac587fc1b4",
            "@type": "oa:Annotation",
            "motivation": "sc:painting",
            "annotatedBy": {
                "name": "OCR"
            },
            "resource": {
                "@type": "cnt:ContentAsText",
                "format": "text/html",
                "chars": "<span id='c4be86d2-8947-4ec7-87d5-b5ac587fc1b4' class='anno-c4be86d2-8947-4ec7-87d5-b5ac587fc1b4' data-letter-spacing='-0.0661764705882353'>.</span>",
                "language": "en"
            },
            "on": {
                "full": "https://readux.io/iiif/v2/t1114/canvas/t1114_00000119.jpg",
                "@type": "oa:SpecificResource",
                "within": {
                    "@id": "https://readux.io/iiif/v2/t1114/manifest",
                    "@type": "sc:Manifest"
                },
                "selector": {
                    "@type": "oa:FragmentSelector",
                    "value": "xywh=6079,4430,17,58",
                    "item": {
                        "@type": "oa:FragmentSelector"
                    }
                }
            },
            "stylesheet": {
                "type": "CssStylesheet",
                "value": ".anno-c4be86d2-8947-4ec7-87d5-b5ac587fc1b4: { height: 58px; width: 17px; font-size: 36.25px; letter-spacing: -1.125px;}"
            }
        },
        {
            "@context": "http://iiif.io/api/presentation/2/context.json",
            "@id": "89de9d11-6f38-4487-be37-bccabf7b230c",
            "@type": "oa:Annotation",
            "motivation": "sc:painting",
            "annotatedBy": {
                "name": "OCR"
            },
            "resource": {
                "@type": "cnt:ContentAsText",
                "format": "text/html",
                "chars": "<span id='89de9d11-6f38-4487-be37-bccabf7b230c' class='anno-89de9d11-6f38-4487-be37-bccabf7b230c' data-letter-spacing='-2.046875'>6</span>",
                "language": "en"
            },
            "on": {
                "full": "https://readux.io/iiif/v2/t1114/canvas/t1114_00000119.jpg",
                "@type": "oa:SpecificResource",
                "within": {
                    "@id": "https://readux.io/iiif/v2/t1114/manifest",
                    "@type": "sc:Manifest"
                },
                "selector": {
                    "@type": "oa:FragmentSelector",
                    "value": "xywh=6086,4312,8,78",
                    "item": {
                        "@type": "oa:FragmentSelector"
                    }
                }
            },
            "stylesheet": {
                "type": "CssStylesheet",
                "value": ".anno-89de9d11-6f38-4487-be37-bccabf7b230c: { height: 78px; width: 8px; font-size: 48.75px; letter-spacing: -16.375px;}"
            }
        }
    ]
}